mcpx_eval/__init__.py
mcpx_eval/__main__.py
mcpx_eval/constants.py
mcpx_eval/database.py
mcpx_eval/html.py
mcpx_eval/htmlgen.py
mcpx_eval/judge.py
mcpx_eval/models.py
mcpx_eval-0.4.3.dist-info/METADATA
mcpx_eval-0.4.3.dist-info/WHEEL
mcpx_eval-0.4.3.dist-info/entry_points.txt
mcpx_eval-0.4.3.dist-info/top_level.txt
mcpx_eval-0.4.3.dist-info/RECORD
