Metadata-Version: 2.4
Name: mcpx-eval
Version: 0.4.3
Summary: Open ended tool use evaluation framework
Requires-Python: >=3.12
Requires-Dist: jinja2>=3.1.5
Requires-Dist: matplotlib>=3.10.0
Requires-Dist: mcp-run>=0.5.0
Requires-Dist: mcpx-py>=0.7.0
Requires-Dist: pandas>=2.2.0
Requires-Dist: pystache>=0.6.7
